setup.py
handlersocket/__init__.py
handlersocket/client.py
handlersocket.egg-info/PKG-INFO
handlersocket.egg-info/SOURCES.txt
handlersocket.egg-info/dependency_links.txt
handlersocket.egg-info/top_level.txt
test/test_encode.py