Metadata-Version: 1.0
Name: handlersocket
Version: 0.0.2
Summary: HandlerSocekt client for Python
Home-page: UNKNOWN
Author: INADA Naoki
Author-email: songofacandy@gmail.com
License: The MIT License
Platform: UNKNOWN
Classifier: Development Status :: 3 - Alpha
Classifier: License :: OSI Approved :: MIT License
Classifier: Topic :: Database
